chromasurr/__init__.py
chromasurr/error_analysis.py
chromasurr/metrics.py
chromasurr/process/batch_elution.py
chromasurr/sensitivity.py
chromasurr/surrogate.py
chromasurr/uq.py
chromasurr/visualize.py
chromasurr-0.1.1.dist-info/AUTHORS.rst
chromasurr-0.1.1.dist-info/LICENSE
chromasurr-0.1.1.dist-info/METADATA
chromasurr-0.1.1.dist-info/WHEEL
chromasurr-0.1.1.dist-info/entry_points.txt
chromasurr-0.1.1.dist-info/RECORD
