Metadata-Version: 2.3
Name: chromasurr
Version: 0.1.1
Summary: Surrogate modeling and Bayesian calibration of chromatographic processes using CADET and Gaussian Processes.
License: MIT
Keywords: chromatography,CADET,surrogate,Bayesian,MCMC
Author: Tala Al-Sunna
Author-email: tala.sunna@gmail.com
Requires-Python: >=3.12,<4
Classifier: License :: OSI Approved :: MIT License
Classifier: Programming Language :: Python :: 3
Classifier: Programming Language :: Python :: 3.12
Classifier: Programming Language :: Python :: 3.13
Requires-Dist: SALib
Requires-Dist: cadet-process (>=0.11.1)
Requires-Dist: emcee
Requires-Dist: matplotlib
Requires-Dist: numpy
Requires-Dist: scikit-learn
Requires-Dist: typer
Project-URL: Documentation, https://talasunna.github.io/chromasurr
Project-URL: Homepage, https://github.com/talasunna/chromasurr
Project-URL: Repository, https://github.com/talasunna/chromasurr
